grading_application/__init__.py
grading_application/app.py
grading_application-0.0.7.dist-info/DESCRIPTION.rst
grading_application-0.0.7.dist-info/METADATA
grading_application-0.0.7.dist-info/RECORD
grading_application-0.0.7.dist-info/WHEEL
grading_application-0.0.7.dist-info/metadata.json
grading_application-0.0.7.dist-info/top_level.txt
