Metadata-Version: 2.0
Name: grading-application
Version: 0.0.7
Summary: Short answer grading assistant with active learning support
Home-page: https://upload.pypi.org/legacy/grading_application
Author: Ravikiran Bhat
Author-email: ravikiranbhat243@gmail.com
License: UNKNOWN
Platform: UNKNOWN
Classifier: Programming Language :: Python :: 3
Classifier: License :: OSI Approved :: MIT License
Classifier: Operating System :: OS Independent
